Metadata-Version: 1.2
Name: remoteit-ssh
Version: 0.3.1
Summary: Opens an SSH connection to a remoteit device by name.
Home-page: https://github.com/conor-f/remoteit-ssh
License: UNKNOWN
Platform: UNKNOWN
Requires-Python: >=3.6
